.DS_Store
lighteda/__init__.py
lighteda-0.0.6.dist-info/LICENSE
lighteda-0.0.6.dist-info/METADATA
lighteda-0.0.6.dist-info/WHEEL
lighteda-0.0.6.dist-info/top_level.txt
lighteda-0.0.6.dist-info/RECORD
