Metadata-Version: 2.1
Name: lighteda
Version: 0.0.6
Summary: A package for exploratoriy data analysis.
Home-page: https://github.com/j84lee/lighteda
Author: Johnny Li
Author-email: l.johnny@outlook.com
License: UNKNOWN
Keywords: EDA,Data Science
Platform: UNKNOWN
Classifier: Programming Language :: Python :: 3
Classifier: License :: OSI Approved :: MIT License
Classifier: Operating System :: OS Independent
